jupyter_commons/__init__.py
jupyter_commons/info.py
jupyter_commons/output.py
jupyter_commons-0.2.1.dist-info/LICENSE
jupyter_commons-0.2.1.dist-info/METADATA
jupyter_commons-0.2.1.dist-info/WHEEL
jupyter_commons-0.2.1.dist-info/top_level.txt
jupyter_commons-0.2.1.dist-info/RECORD
