Metadata-Version: 2.1
Name: jupyter-commons
Version: 0.2.1
Summary: Commonly used helpers for jupyter notebooks.
Home-page: https://github.com/stbraun/jupyter_commons
Author: Stefan Braun
Author-email: sb@stbraun.com
License: BSD license
Keywords: jupyter_commons
Platform: UNKNOWN
Classifier: Development Status :: 4 - Beta 
Classifier: Intended Audience :: Developers
Classifier: License :: OSI Approved :: BSD License
Classifier: Natural Language :: English
Classifier: Programming Language :: Python :: 3
Classifier: Programming Language :: Python :: 3.7
Classifier: Programming Language :: Python :: 3.8
Requires: ipython
Requires-Dist: ipython
